Metadata-Version: 2.1
Name: partpyth
Version: 0.1
Summary: PythonBased
